gguf_us/__init__.py
gguf_us/__main__.py
gguf_us-0.0.2.dist-info/LICENSE
gguf_us-0.0.2.dist-info/WHEEL
gguf_us-0.0.2.dist-info/METADATA
gguf_us-0.0.2.dist-info/RECORD
