Metadata-Version: 2.1
Name: gguf-us
Version: 0.0.2
Summary: localhost for gguf.us
Author-email: gguf <info@gguf.us>
Classifier: License :: OSI Approved :: MIT License
Project-URL: Repository, https://github.com/gguf-org/frontend
